{
  "Button": 1130,
  "TextInput": 379,
  "Notification": 269,
  "Checkbox": 138,
  "IconCross": 122,
  "Select": 120,
  "LoadingSpinner": 106,
  "IconArrowRight": 102,
  "Dialog.Content": 95,
  "RadioButton": 94,
  "Link": 93,
  "Footer.Link": 83,
  "IconAngleDown": 81,
  "DateInput": 80,
  "Dialog.ActionButtons": 79,
  "Dialog": 75,
  "Dialog.Header": 75,
  "TextArea": 74,
  "IconLinkExternal": 72,
  "IconLocation": 72,
  "IconPen": 72,
  "IconAngleRight": 71,
  "IconPlus": 71,
  "IconArrowLeft": 68,
  "IconAngleUp": 66,
  "IconCheck": 62,
  "SelectionGroup": 60,
  "IconInfoCircle": 59,
  "IconSearch": 59,
  "Accordion": 53,
  "Tabs.Tab": 51,
  "Container": 50,
  "Tabs.TabPanel": 50,
  "IconTrash": 49,
  "Koros": 45,
  "Card": 44,
  "Fieldset": 43,
  "IconClock": 42,
  "Navigation.Item": 42,
  "IconCrossCircle": 40,
  "Logo": 40,
  "Tab": 40,
  "Tooltip": 38,
  "Combobox": 37,
  "TabPanel": 36,
  "Tabs": 36,
  "StatusLabel": 34,
  "IconAlertCircleFill": 33,
  "IconAngleLeft": 32,
  "Footer.Item": 31,
  "IconAlertCircle": 31,
  "Table": 30,
  "Footer": 29,
  "Footer.Base": 29,
  "IconCheckCircleFill": 29,
  "IconGroup": 29,
  "IconPlusCircle": 29,
  "IconUser": 29,
  "IconDownload": 28,
  "IconSignout": 27,
  "Tag": 27,
  "IconQuestionCircle": 24,
  "IconCogwheel": 21,
  "LoginProvider": 20,
  "IconCalendar": 19,
  "IconCalendarClock": 19,
  "IconLock": 18,
  "IconPenLine": 18,
  "NumberInput": 18,
  "SearchInput": 18,
  "CookieModal": 17,
  "Header.Link": 17,
  "IconTicket": 17,
  "Header": 16,
  "Header.ActionBar": 16,
  "Header.ActionBarItem": 16,
  "TabList": 16,
  "Tabs.TabList": 16,
  "FileInput": 15,
  "IconMinus": 15,
  "IconArrowUndo": 14,
  "IconCheckCircle": 14,
  "IconEnvelope": 14,
  "LoginCallbackHandler": 14,
  "Navigation": 14,
  "Footer.Navigation": 13,
  "Header.LanguageSelector": 13,
  "IconCalendarPlus": 13,
  "IconEye": 13,
  "IconSignin": 13,
  "Navigation.Actions": 13,
  "Pagination": 13,
  "Header.NavigationMenu": 12,
  "IconDocument": 12,
  "IconEuroSign": 12,
  "Navigation.Row": 12,
  "Header.SkipLink": 11,
  "IconLayers": 11,
  "TimeInput": 11,
  "CookiePage": 10,
  "ErrorSummary": 10,
  "Footer.Utilities": 10,
  "IconArrowUp": 10,
  "IconCrossCircleFill": 10,
  "IconLink": 10,
  "IconSaveDiskette": 10,
  "IconArrowDown": 9,
  "IconPhoto": 9,
  "IconSpeechbubbleText": 9,
  "IconMap": 8,
  "IconMenuDots": 8,
  "IconUpload": 8,
  "Navigation.User": 8,
  "Stepper": 8,
  "Header.ActionBarButton": 7,
  "IconHome": 7,
  "IconMinusCircle": 7,
  "IconPrinter": 7,
  "IconSortDescending": 7,
  "IconStar": 7,
  "SideNavigation.MainLevel": 7,
  "ToggleButton": 7,
  "WithAuthentication": 7,
  "IconError": 6,
  "IconFaceSmile": 6,
  "IconFacebook": 6,
  "IconGlobe": 6,
  "IconHistory": 6,
  "IconLockOpen": 6,
  "IconPersonWheelchair": 6,
  "IconPlusCircleFill": 6,
  "IconSortAscending": 6,
  "IconStarFill": 6,
  "Linkbox": 6,
  "Navigation.LanguageSelector": 6,
  "PhoneInput": 6,
  "SessionEndedHandler": 6,
  "Header.LoginButton": 5,
  "IconClose": 5,
  "IconCopy": 5,
  "IconInfoCircleFill": 5,
  "IconPhone": 5,
  "IconPlaybackNext": 5,
  "IconQuestionCircleFill": 5,
  "IconSort": 5,
  "Breadcrumb": 4,
  "IconArrowRedo": 4,
  "IconBell": 4,
  "IconCake": 4,
  "IconErrorFill": 4,
  "IconEyeCrossed": 4,
  "IconInfo": 4,
  "IconLinkedin": 4,
  "SideNavigation": 4,
  "Footer.GroupHeading": 3,
  "Header.ActionBarSubItem": 3,
  "Header.SimpleLanguageOptions": 3,
  "IconMenuHamburger": 3,
  "IconPaperclip": 3,
  "IconSaveDisketteFill": 3,
  "IconSpeechbubble": 3,
  "IconTwitter": 3,
  "IconX": 3,
  "LoginButton": 3,
  "SideNavigation.SubLevel": 3,
  "Footer.UtilityGroup": 2,
  "Header.LogoutSubmenuButton": 2,
  "IconArrowTopRight": 2,
  "IconCalendarCross": 2,
  "IconClockPlus": 2,
  "IconCogwheels": 2,
  "IconCompany": 2,
  "IconFaceSad": 2,
  "IconFood": 2,
  "IconHeart": 2,
  "IconInstagram": 2,
  "IconMinusCircleFill": 2,
  "RoundedTag": 2,
  "DismissableNotification": 1,
  "Dropdown": 1,
  "Footer.ItemGroup": 1,
  "Footer.NavigationGroup": 1,
  "Header.UniversalBar": 1,
  "Header.UserMenuButton": 1,
  "IconArrowBottomRight": 1,
  "IconArrowRightDashed": 1,
  "IconBagCogwheel": 1,
  "IconBinoculars": 1,
  "IconBox": 1,
  "IconCalendarRecurring": 1,
  "IconFamily": 1,
  "IconGlyphEuro": 1,
  "IconGraphColumns": 1,
  "IconKey": 1,
  "IconMenu": 1,
  "IconMoneyBag": 1,
  "IconMover": 1,
  "IconPersonGenderless": 1,
  "IconPhotoPlus": 1,
  "IconRestaurant": 1,
  "IconScrollCogwheel": 1,
  "IconSenior": 1,
  "IconSortAlphabeticalAscending": 1,
  "IconSortAlphabeticalDescending": 1,
  "IconTextTool": 1,
  "IconThumbsUp": 1,
  "IconUploadCloud": 1,
  "IconYouth": 1,
  "IconYoutube": 1,
  "ImageWithCard": 1,
  "Navigation.Search": 1,
  "StepByStep": 1
}